odoo10_addon_l10n_it_esigibilita_iva-10.0.1.0.0-py2.7-nspkg.pth
odoo/addons/l10n_it_esigibilita_iva/README.rst
odoo/addons/l10n_it_esigibilita_iva/__init__.py
odoo/addons/l10n_it_esigibilita_iva/__manifest__.py
odoo/addons/l10n_it_esigibilita_iva/i18n/it.po
odoo/addons/l10n_it_esigibilita_iva/models/__init__.py
odoo/addons/l10n_it_esigibilita_iva/models/account.py
odoo/addons/l10n_it_esigibilita_iva/static/description/icon.png
odoo/addons/l10n_it_esigibilita_iva/views/account_view.xml
odoo10_addon_l10n_it_esigibilita_iva-10.0.1.0.0.dist-info/DESCRIPTION.rst
odoo10_addon_l10n_it_esigibilita_iva-10.0.1.0.0.dist-info/METADATA
odoo10_addon_l10n_it_esigibilita_iva-10.0.1.0.0.dist-info/RECORD
odoo10_addon_l10n_it_esigibilita_iva-10.0.1.0.0.dist-info/WHEEL
odoo10_addon_l10n_it_esigibilita_iva-10.0.1.0.0.dist-info/metadata.json
odoo10_addon_l10n_it_esigibilita_iva-10.0.1.0.0.dist-info/namespace_packages.txt
odoo10_addon_l10n_it_esigibilita_iva-10.0.1.0.0.dist-info/top_level.txt
